{
  "$schema": "https://developer.microsoft.com/json-schemas/spfx-build/package-solution.schema.json",
  "solution": {
    "name": "crud-5-client-side-solution",
    "id": "038e37a1-3eb7-4bf7-87f1-10c96d1dba02",
    "version": "1.0.0.0",
    "includeClientSideAssets": true,
    "skipFeatureDeployment": true,
    "isDomainIsolated": false,
    "developer": {
      "name": "",
      "websiteUrl": "",
      "privacyUrl": "",
      "termsOfUseUrl": "",
      "mpnId": "Undefined-1.16.1"
    },
    "metadata": {
      "shortDescription": {
        "default": "crud-5 description"
      },
      "longDescription": {
        "default": "crud-5 description"
      },
      "screenshotPaths": [],
      "videoUrl": "",
      "categories": []
    },
    "features": [
      {
        "title": "crud-5 Feature",
        "description": "The feature that activates elements of the crud-5 solution.",
        "id": "41a3b86c-ef4b-47f1-a3c0-fa829cd8e28f",
        "version": "1.0.0.0"
      }
    ]
  },
  "paths": {
    "zippedPackage": "solution/crud-5.sppkg"
  }
}
